ruphon/__init__.py
ruphon/char_tokenizer.py
ruphon/ruphon.py
ruphon/.ipynb_checkpoints/__init__-checkpoint.py
ruphon/.ipynb_checkpoints/char_tokenizer-checkpoint.py
ruphon/.ipynb_checkpoints/ruphon-checkpoint.py
ruphon-1.3.dist-info/LICENSE
ruphon-1.3.dist-info/WHEEL
ruphon-1.3.dist-info/METADATA
ruphon-1.3.dist-info/RECORD
