Metadata-Version: 2.1
Name: ruphon
Version: 1.3
Summary: Russian phonemizer
Author-email: "Denis Petrov, Ivan Shivalov" <arduino4b@gmail.com>
Requires-Dist: huggingface_hub
Requires-Dist: onnxruntime
Requires-Dist: transformers
Requires-Dist: numpy
Requires-Dist: razdel
Project-URL: Home, https://github.com/Den4ikAI/ruphon
